chatgpt_conversation_finder/__init__.py
chatgpt_conversation_finder/chats_json_handler.py
chatgpt_conversation_finder/config.py
chatgpt_conversation_finder/constants.py
chatgpt_conversation_finder/data/default_config.ini
chatgpt_conversation_finder/data/nltk_data/corpora/stopwords/english
chatgpt_conversation_finder/edit_file.py
chatgpt_conversation_finder/exceptions.py
chatgpt_conversation_finder/file_dialog.py
chatgpt_conversation_finder/grep_handler.py
chatgpt_conversation_finder/gui.py
chatgpt_conversation_finder/helpers.py
chatgpt_conversation_finder/index_manager.py
chatgpt_conversation_finder/main.py
chatgpt_conversation_finder/prefix_index_manager.py
chatgpt_conversation_finder/quick_search.py
chatgpt_conversation_finder/sanitizer.py
chatgpt_conversation_finder/validate_conversations.py
chatgpt_conversation_finder/word_index_manager.py
chatgpt_conversation_finder-0.2.0.dist-info/LICENSE
chatgpt_conversation_finder-0.2.0.dist-info/METADATA
chatgpt_conversation_finder-0.2.0.dist-info/WHEEL
chatgpt_conversation_finder-0.2.0.dist-info/entry_points.txt
chatgpt_conversation_finder-0.2.0.dist-info/RECORD
