Metadata-Version: 2.1
Name: chatgpt-conversation-finder
Version: 0.2.0
Summary: 
Author: Håkon Hægland
Author-email: hakon.hagland@gmail.com
Requires-Python: >=3.11,<4.0
Classifier: Programming Language :: Python :: 3
Classifier: Programming Language :: Python :: 3.11
Classifier: Programming Language :: Python :: 3.12
Requires-Dist: click (>=8.1.7,<9.0.0)
Requires-Dist: colorama (>=0.4.6,<0.5.0)
Requires-Dist: nltk (>=3.8.1,<4.0.0)
Requires-Dist: platformdirs (>=4.2.0,<5.0.0)
Requires-Dist: pyqt6 (>=6.6.1,<7.0.0)
Requires-Dist: sphinx-click-rst-to-ansi-formatter (>=0.1.0,<0.2.0)
